Metadata-Version: 1.1
Name: radu
Version: 0.0.1
Summary: A very basic radu
Home-page: UNKNOWN
Author: WebmgoCreator
Author-email: mihai.gorunescu@webmgo.ro
License: MIT
Keywords: radu
Platform: UNKNOWN
Classifier: Development Status :: 5 - Production/Stable
Classifier: Intended Audience :: Education
Classifier: Operating System :: Microsoft :: Windows :: Windows 10
Classifier: License :: OSI Approved :: MIT License
Classifier: Programming Language :: Python :: 3
